Workbook
Name Slicer_Category: #N/A
Name Slicer_City: #N/A
Name Slicer_Months__Order_Date: #N/A
Name Slicer_Payment_Method: #N/A
Name tblCities: Table214[Cities]
Name tblCoffeeSales: Sales_Data!$A$1:$P$1001
Name tblOrdertype: Table416[[#All],[Order Type]]
Name tblPayment: Table315[[#All],[Payment Methods]]
Name tblProducts: Table18[Product]
Name tblRating: Table517[[#All],[Customer Rating]]
Name tblSalespersons: Table618[[#All],[Salespersons]]

Sheet Lists
A1: Product | B1: Category | C1: Unit_Price | D1: Cost_Price | F1: Cities | H1: Payment Methods | J1: Order Type | L1: Customer Rating | N1: Salespersons | P1: Customer_Name
A2: Espresso | B2: Coffee | C2: 120 | D2: 60 | F2: Mumbai | H2: Cash | J2: Dine-In | L2: 1 | N2: Aarav | P2: Aarav Sharma
A3: Cappuccino | B3: Coffee | C3: 180 | D3: 90 | F3: Delhi | H3: UPI | J3: Takeaway | L3: 2 | N3: Priya | P3: Priya Patel
A4: Latte | B4: Coffee | C4: 200 | D4: 100 | F4: Bengaluru | H4: Credit Card | J4: Delivery | L4: 3 | N4: Rahul | P4: Rahul Verma
A5: Americano | B5: Coffee | C5: 150 | D5: 75 | F5: Hyderabad | H5: Debit Card | L5: 4 | N5: Neha | P5: Neha Gupta
A6: Mocha | B6: Coffee | C6: 220 | D6: 110 | F6: Pune | H6: Wallet | L6: 5 | N6: Rohan | P6: Rohan Mehta
A7: Cold Coffee | B7: Cold Beverage | C7: 190 | D7: 95 | F7: Chennai | N7: Ananya | P7: Ananya Singh
A8: Iced Latte | B8: Cold Beverage | C8: 210 | D8: 105 | F8: Kolkata | N8: Vikram | P8: Vikram Rao
A9: Hot Chocolate | B9: Beverage | C9: 170 | D9: 85 | F9: Ahmedabad | N9: Sneha | P9: Sneha Nair
A10: Green Tea | B10: Tea | C10: 140 | D10: 70 | F10: Jaipur | N10: Karan | P10: Karan Joshi
A11: Black Tea | B11: Tea | C11: 120 | D11: 60 | F11: Goa | N11: Pooja | P11: Pooja Kulkarni
A12: Blueberry Muffin | B12: Bakery | C12: 110 | D12: 55 | P12: Aditya Kumar
A13: Chocolate Brownie | B13: Bakery | C13: 130 | D13: 65 | P13: Nisha Sharma
A14: Croissant | B14: Bakery | C14: 150 | D14: 75 | P14: Arjun Reddy
A15: Veg Sandwich | B15: Snacks | C15: 180 | D15: 90 | P15: Kavya Iyer
A16: Chicken Sandwich | B16: Snacks | C16: 220 | D16: 110 | P16: Aman Mishra
A17: French Fries | B17: Snacks | C17: 160 | D17: 80 | P17: Meera Desai
A18: Garlic Bread | B18: Snacks | C18: 170 | D18: 85 | P18: Siddharth Jain
A19: Cheesecake | B19: Dessert | C19: 240 | D19: 120 | P19: Divya Shetty
A20: Donut | B20: Dessert | C20: 100 | D20: 50 | P20: Yash Patil
A21: Cookie | B21: Dessert | C21: 80 | D21: 40 | P21: Ishita Roy
P22: Harsh Vyas
P23: Aditi Kapoor
P24: Manish Yadav
P25: Simran Kaur
P26: Akash Naik
P27: Ritika Das
P28: Mohit Agarwal
P29: Tanvi Bhat
P30: Vivek Nair
P31: Shruti Rao

Sheet Sales_Data
A1: Order_ID | B1: Order_Date | C1: Customer_Name | D1: City | E1: Product | F1: Category | G1: Quantity | H1: Unit_Price | I1: Cost_Price | J1: Discount | K1: Total_Sales | L1: Profit | M1: Payment_Method | N1: Order_Type | O1: Salesperson | P1: Customer_Rating
A2: ="ORD"&TEXT(ROW()-1,"0000") -> ORD0001 | B2: 46343 | C2: Aditya Kumar | D2: Chennai | E2: Cheesecake | F2: Dessert | G2: 2 | H2: =_xlfn.XLOOKUP(E2,Table18[Product],Table18[Unit_Price]) -> 240 | I2: =_xlfn.XLOOKUP(E2,Table18[Product],Table18[Cost_Price]) -> 120 | J2: 18 | K2: =(G2*H2)-J2 -> 462 | L2: =K2-(G2*I2) -> 222 | M2: UPI | N2: Delivery | O2: Rahul | P2: 4
A3: ="ORD"&TEXT(ROW()-1,"0000") -> ORD0002 | B3: 46383 | C3: Vikram Rao | D3: Hyderabad | E3: Green Tea | F3: Tea | G3: 2 | H3: =_xlfn.XLOOKUP(E3,Table18[Product],Table18[Unit_Price]) -> 140 | I3: =_xlfn.XLOOKUP(E3,Table18[Product],Table18[Cost_Price]) -> 70 | J3: 24 | K3: =(G3*H3)-J3 -> 256 | L3: =K3-(G3*I3) -> 116 | M3: Credit Card | N3: Takeaway | O3: Sneha | P3: 4
A4: ="ORD"&TEXT(ROW()-1,"0000") -> ORD0003 | B4: 46296 | C4: Divya Shetty | D4: Hyderabad | E4: Blueberry Muffin | F4: Bakery | G4: 1 | H4: =_xlfn.XLOOKUP(E4,Table18[Product],Table18[Unit_Price]) -> 110 | I4: =_xlfn.XLOOKUP(E4,Table18[Product],Table18[Cost_Price]) -> 55 | J4: 24 | K4: =(G4*H4)-J4 -> 86 | L4: =K4-(G4*I4) -> 31 | M4: Wallet | N4: Delivery | O4: Vikram | P4: 4
A5: ="ORD"&TEXT(ROW()-1,"0000") -> ORD0004 | B5: 46097 | C5: Simran Kaur | D5: Ahmedabad | E5: Cappuccino | F5: Coffee | G5: 3 | H5: =_xlfn.XLOOKUP(E5,Table18[Product],Table18[Unit_Price]) -> 180 | I5: =_xlfn.XLOOKUP(E5,Table18[Product],Table18[Cost_Price]) -> 90 | J5: 50 | K5: =(G5*H5)-J5 -> 490 | L5: =K5-(G5*I5) -> 220 | M5: Debit Card | N5: Dine-In | O5: Rohan | P5: 4
A6: ="ORD"&TEXT(ROW()-1,"0000") -> ORD0005 | B6: 46367 | C6: Priya Patel | D6: Goa | E6: Cappuccino | F6: Coffee | G6: 1 | H6: =_xlfn.XLOOKUP(E6,Table18[Product],Table18[Unit_Price]) -> 180 | I6: =_xlfn.XLOOKUP(E6,Table18[Product],Table18[Cost_Price]) -> 90 | J6: 6 | K6: =(G6*H6)-J6 -> 174 | L6: =K6-(G6*I6) -> 84 | M6: Credit Card | N6: Takeaway | O6: Pooja | P6: 3
A7: ="ORD"&TEXT(ROW()-1,"0000") -> ORD0006 | B7: 46286 | C7: Aman Mishra | D7: Pune | E7: French Fries | F7: Snacks | G7: 2 | H7: =_xlfn.XLOOKUP(E7,Table18[Product],Table18[Unit_Price]) -> 160 | I7: =_xlfn.XLOOKUP(E7,Table18[Product],Table18[Cost_Price]) -> 80 | J7: 5 | K7: =(G7*H7)-J7 -> 315 | L7: =K7-(G7*I7) -> 155 | M7: Debit Card | N7: Dine-In | O7: Vikram | P7: 5
A8: ="ORD"&TEXT(ROW()-1,"0000") -> ORD0007 | B8: 46160 | C8: Akash Naik | D8: Chennai | E8: Chicken Sandwich | F8: Snacks | G8: 5 | H8: =_xlfn.XLOOKUP(E8,Table18[Product],Table18[Unit_Price]) -> 220 | I8: =_xlfn.XLOOKUP(E8,Table18[Product],Table18[Cost_Price]) -> 110 | J8: 28 | K8: =(G8*H8)-J8 -> 1072 | L8: =K8-(G8*I8) -> 522 | M8: Credit Card | N8: Takeaway | O8: Rohan | P8: 4
A9: ="ORD"&TEXT(ROW()-1,"0000") -> ORD0008 | B9: 46313 | C9: Aditya Kumar | D9: Pune | E9: French Fries | F9: Snacks | G9: 3 | H9: =_xlfn.XLOOKUP(E9,Table18[Product],Table18[Unit_Price]) -> 160 | I9: =_xlfn.XLOOKUP(E9,Table18[Product],Table18[Cost_Price]) -> 80 | J9: 19 | K9: =(G9*H9)-J9 -> 461 | L9: =K9-(G9*I9) -> 221 | M9: Wallet | N9: Takeaway | O9: Aarav | P9: 3
A10: ="ORD"&TEXT(ROW()-1,"0000") -> ORD0009 | B10: 46209 | C10: Pooja Kulkarni | D10: Pune | E10: Donut | F10: Dessert | G10: 3 | H10: =_xlfn.XLOOKUP(E10,Table18[Product],Table18[Unit_Price]) -> 100 | I10: =_xlfn.XLOOKUP(E10,Table18[Product],Table18[Cost_Price]) -> 50 | J10: 33 | K10: =(G10*H10)-J10 -> 267 | L10: =K10-(G10*I10) -> 117 | M10: UPI | N10: Delivery | O10: Neha | P10: 5
A11: ="ORD"&TEXT(ROW()-1,"0000") -> ORD0010 | B11: 46029 | C11: Meera Desai | D11: Chennai | E11: Americano | F11: Coffee | G11: 1 | H11: =_xlfn.XLOOKUP(E11,Table18[Product],Table18[Unit_Price]) -> 150 | I11: =_xlfn.XLOOKUP(E11,Table18[Product],Table18[Cost_Price]) -> 75 | J11: 45 | K11: =(G11*H11)-J11 -> 105 | L11: =K11-(G11*I11) -> 30 | M11: Debit Card | N11: Takeaway | O11: Vikram | P11: 4
A12: ="ORD"&TEXT(ROW()-1,"0000") -> ORD0011 | B12: 46292 | C12: Pooja Kulkarni | D12: Kolkata | E12: Americano | F12: Coffee | G12: 1 | H12: =_xlfn.XLOOKUP(E12,Table18[Product],Table18[Unit_Price]) -> 150 | I12: =_xlfn.XLOOKUP(E12,Table18[Product],Table18[Cost_Price]) -> 75 | J12: 37 | K12: =(G12*H12)-J12 -> 113 | L12: =K12-(G12*I12) -> 38 | M12: Debit Card | N12: Dine-In | O12: Aarav | P12: 3
A13: ="ORD"&TEXT(ROW()-1,"0000") -> ORD0012 | B13: 46292 | C13: Aarav Sharma | D13: Pune | E13: Cheesecake | F13: Dessert | G13: 5 | H13: =_xlfn.XLOOKUP(E13,Table18[Product],Table18[Unit_Price]) -> 240 | I13: =_xlfn.XLOOKUP(E13,Table18[Product],Table18[Cost_Price]) -> 120 | J13: 3 | K13: =(G13*H13)-J13 -> 1197 | L13: =K13-(G13*I13) -> 597 | M13: Credit Card | N13: Dine-In | O13: Pooja | P13: 3
... A1001: ="ORD"&TEXT(ROW()-1,"0000") -> ORD1000 | B1001: 46055 | C1001: Siddharth Jain | D1001: Mumbai | E1001: Green Tea | F1001: Tea | G1001: 2 | H1001: =_xlfn.XLOOKUP(E1001,Table18[Product],Table18[Unit_Price]) -> 140 | I1001: =_xlfn.XLOOKUP(E1001,Table18[Product],Table18[Cost_Price]) -> 70 | J1001: 22 | K1001: =(G1001*H1001)-J1001 -> 258 | L1001: =K1001-(G1001*I1001) -> 118 | M1001: UPI | N1001: Dine-In | O1001: Aarav | P1001: 5

Sheet Sheet1
A2: Total Revenue
A3: 39148
A7: Total Orders
A8: 86
A13: Total Customers
A14: 86
A17: Total Profit
A18: 18458
A21: Average Order Value
A22: 455.2093
A26: =GETPIVOTDATA("Total_Sales",Sheet1!$A$2) -> 39148
A27: =GETPIVOTDATA("Order_ID",Sheet1!$A$7) -> 86
A28: =GETPIVOTDATA("Customer_Name",Sheet1!$A$13) -> 86
A29: =GETPIVOTDATA("Profit",Sheet1!$A$17) -> 18458
A30: =GETPIVOTDATA("Total_Sales",Sheet1!$A$21) -> 455.2093

Sheet Pivot
A1: Row Labels | B1: Sum of Total_Sales | D1: Row Labels | E1: Sum of Total_Sales | G1: Row Labels | H1: Sum of Total_Sales | J1: Row Labels | K1: Sum of Total_Sales | M1: Row Labels | N1: Count of Total_Sales
A2: Americano | B2: 7817 | D2: Bakery | E2: 11365 | G2: Ahmedabad | H2: 3545 | J2: Americano | K2: 7817 | M2: 3 | N2: 26
A3: Blueberry Muffin | B3: 5302 | D3: Coffee | E3: 31904 | G3: Chennai | H3: 6538 | J3: Latte | K3: 7665 | M3: 4 | N3: 31
A4: Cappuccino | B4: 5124 | D4: Grand Total | E4: 43269 | G4: Delhi | H4: 4534 | J4: Mocha | K4: 6763 | M4: 5 | N4: 29
A5: Chocolate Brownie | B5: 1164 | G5: Goa | H5: 3515 | J5: Blueberry Muffin | K5: 5302 | M5: Grand Total | N5: 86
A6: Croissant | B6: 2938 | G6: Hyderabad | H6: 4517 | J6: Cappuccino | K6: 5124
A7: Espresso | B7: 2375 | G7: Jaipur | H7: 3055 | J7: Croissant | K7: 2938
A8: Latte | B8: 7665 | G8: Kolkata | H8: 3045 | J8: Espresso | K8: 2375
A9: Mocha | B9: 6763 | G9: Mumbai | H9: 6486 | J9: Chocolate Brownie | K9: 1164
A10: Grand Total | B10: 39148 | G10: Pune | H10: 3913 | J10: Grand Total | K10: 39148
G11: Grand Total | H11: 39148
D12: Row Labels | E12: Sum of Total_Sales
D13: Jan | E13: 11036
D14: Feb | E14: 8613 | G14: Row Labels | H14: Count of Order_ID | J14: Row Labels | K14: Sum of Total_Sales
D15: Mar | E15: 12753 | G15: Cash | H15: 25 | J15: Aarav | K15: 2924
D16: Jun | E16: 6746 | G16: Credit Card | H16: 25 | J16: Ananya | K16: 3791
D17: Grand Total | E17: 39148 | G17: UPI | H17: 15 | J17: Karan | K17: 4975
G18: Wallet | H18: 21 | J18: Neha | K18: 3317
G19: Grand Total | H19: 86 | J19: Pooja | K19: 4389
J20: Priya | K20: 3024
J21: Rahul | K21: 5283
J22: Rohan | K22: 2960
J23: Sneha | K23: 5084
J24: Vikram | K24: 3401
J25: Grand Total | K25: 39148

Sheet Dashboard
A1: Coffee Shop Sales Performance Dashboard
